filerepo/__init__.py
filerepo/__main__.py
filerepo/repomanager.py
tree_file_repo-0.2.dist-info/METADATA
tree_file_repo-0.2.dist-info/RECORD
tree_file_repo-0.2.dist-info/WHEEL
tree_file_repo-0.2.dist-info/top_level.txt
