Metadata-Version: 2.1
Name: tree-file-repo
Version: 0.2
Summary: 3-file-repo is a python package for saving files in a tree-folder-structure way
Home-page: https://github.com/agencianacionaldigital/3-file-repo
Author: Agencia Nacional Digital
Author-email: agencianacionaldigital@and.gov.co
License: MIT
Platform: UNKNOWN
